clean_confluent_kafka/__about__.py
clean_confluent_kafka/__init__.py
clean_confluent_kafka/__main__.py
clean_confluent_kafka/application.py
clean_confluent_kafka/config.py
clean_confluent_kafka/connection.py
clean_confluent_kafka/tools.py
clean_confluent_kafka/resources/base-kafka.yaml
clean_confluent_kafka/resources/kafka-template.yaml
clean_confluent_kafka/utils/__init__.py
clean_confluent_kafka/utils/deserializers.py
clean_confluent_kafka/utils/serializers.py
clean_confluent_kafka-0.6.1.dist-info/METADATA
clean_confluent_kafka-0.6.1.dist-info/WHEEL
clean_confluent_kafka-0.6.1.dist-info/RECORD
