Metadata-Version: 2.1
Name: clean_confluent_kafka
Version: 0.6.1
Summary: a clean interface for confluent_kafka
Project-URL: Documentation, https://github.com/mohammadraziei/clean-confluent-kafka#readme
Project-URL: Issues, https://github.com/mohammadraziei/clean-confluent-kafka/issues
Project-URL: Source, https://github.com/mohammadraziei/clean-confluent-kafka
Author-email: mohammadraziei <mohammadraziei1375@gmail.com>
License-Expression: MIT
Classifier: Development Status :: 4 - Beta
Classifier: Programming Language :: Python
Classifier: Programming Language :: Python :: 3.7
Classifier: Programming Language :: Python :: 3.8
Classifier: Programming Language :: Python :: 3.9
Classifier: Programming Language :: Python :: 3.10
Classifier: Programming Language :: Python :: 3.11
Classifier: Programming Language :: Python :: Implementation :: CPython
Classifier: Programming Language :: Python :: Implementation :: PyPy
Requires-Python: >=3.7
Requires-Dist: confluent-kafka
Requires-Dist: fastnumbers
Requires-Dist: jinja2
Requires-Dist: pyyaml
